audyn/__init__.py
audyn/_cpp_extensions/monotonic_align.cpython-312-darwin.so
audyn/bin/decode_musdb18.py
audyn/bin/download_mtat.py
audyn/bin/download_mtg_jamendo.py
audyn/bin/download_musdb18.py
audyn/bin/download_openmic2018.py
audyn/bin/parse_run_command.py
audyn/configs/config.yaml
audyn/configs/decode-musdb18.yaml
audyn/configs/download-mtat.yaml
audyn/configs/download-mtg-jamendo.yaml
audyn/configs/download-musdb18.yaml
audyn/configs/download-openmic2018.yaml
audyn/configs/criterion/cross_entropy.yaml
audyn/configs/criterion/vqvae.yaml
audyn/configs/data/defaults.yaml
audyn/configs/lr_scheduler/defaults.yaml
audyn/configs/lr_scheduler/none.yaml
audyn/configs/lr_scheduler/transformer.yaml
audyn/configs/model/defaults.yaml
audyn/configs/model/gan.yaml
audyn/configs/optimizer/adam.yaml
audyn/configs/optimizer/adam_ema.yaml
audyn/configs/optimizer/adamw.yaml
audyn/configs/optimizer/gan.yaml
audyn/configs/preprocess/defaults.yaml
audyn/configs/preprocess/ljspeech_text-to-feat.yaml
audyn/configs/preprocess/text-to-feat.yaml
audyn/configs/preprocess/text-to-wave.yaml
audyn/configs/system/cpu.yaml
audyn/configs/system/cuda.yaml
audyn/configs/system/cuda_amp.yaml
audyn/configs/system/cuda_ddp.yaml
audyn/configs/system/cuda_ddp_amp.yaml
audyn/configs/system/defaults.yaml
audyn/configs/system/mps.yaml
audyn/configs/test/defaults.yaml
audyn/configs/test/text_to_wave.yaml
audyn/configs/test/dataloader/defaults.yaml
audyn/configs/test/dataset/defaults.yaml
audyn/configs/test/dataset/torch.yaml
audyn/configs/train/defaults.yaml
audyn/configs/train/gan.yaml
audyn/configs/train/template.yaml
audyn/configs/train/text-to-feat+pretrained_feat-to-wave.yaml
audyn/configs/train/clip_gradient/defaults.yaml
audyn/configs/train/clip_gradient/gan.yaml
audyn/configs/train/dataloader/defaults.yaml
audyn/configs/train/dataloader/sequential-batch.yaml
audyn/configs/train/dataset/defaults.yaml
audyn/configs/train/dataset/random-stems-musdb18.yaml
Audyn-0.0.3.dist-info/LICENSE
Audyn-0.0.3.dist-info/METADATA
Audyn-0.0.3.dist-info/WHEEL
Audyn-0.0.3.dist-info/entry_points.txt
Audyn-0.0.3.dist-info/top_level.txt
Audyn-0.0.3.dist-info/RECORD
