Metadata-Version: 2.1
Name: Audyn
Version: 0.0.3
Summary: A PyTorch toolkit for audio synthesis.
Author: Takuya Hasumi
License: Apache License
Project-URL: url, https://github.com/tky823/Audyn
Requires-Python: <4,>=3.8
License-File: LICENSE
Requires-Dist: omegaconf
Requires-Dist: hydra-core
Requires-Dist: torch
Requires-Dist: torchaudio
Requires-Dist: torchtext
Requires-Dist: torchvision
Requires-Dist: tensorboard
Requires-Dist: numpy<2.0
Requires-Dist: webdataset
Requires-Dist: inflect
Requires-Dist: importlib-resources<6.2; python_version == "3.8"
Requires-Dist: matplotlib; sys_platform != "win32"
Requires-Dist: matplotlib<3.9.1; sys_platform == "win32"
Provides-Extra: dev
Requires-Dist: flake8; extra == "dev"
Requires-Dist: black; extra == "dev"
Requires-Dist: isort; extra == "dev"
Provides-Extra: docs
Requires-Dist: sphinx; extra == "docs"
Requires-Dist: sphinx-autodoc-typehints; extra == "docs"
Requires-Dist: sphinx-autobuild; extra == "docs"
Requires-Dist: nbsphinx; extra == "docs"
Requires-Dist: furo; extra == "docs"
Provides-Extra: recipes
Requires-Dist: tqdm; extra == "recipes"
Provides-Extra: tests
Requires-Dist: pytest; extra == "tests"
Requires-Dist: pytest-cov; extra == "tests"
